clio/__init__.py
clio/client.py
clio/config.py
clio/exceptions.py
clio/logger.py
clio/uploader.py
clio/utils.py
clio_monitoring-0.1.10.dist-info/METADATA
clio_monitoring-0.1.10.dist-info/WHEEL
clio_monitoring-0.1.10.dist-info/RECORD
