Metadata-Version: 2.4
Name: clio_monitoring
Version: 0.1.10
Summary: Playwright automation monitoring SDK
Project-URL: Homepage, https://docs.cliomonitoring.com
Project-URL: Documentation, https://docs.cliomonitoring.com
Project-URL: Repository, https://github.com/TreebeardHQ/clio-python-sdk
Project-URL: Issues, https://github.com/TreebeardHQ/clio-python-sdk/issues
Author-email: Clio Team <info@treebeardhq.com>
Keywords: automation,monitoring,playwright,testing
Classifier: Development Status :: 3 - Alpha
Classifier: Intended Audience :: Developers
Classifier: License :: OSI Approved :: MIT License
Classifier: Programming Language :: Python :: 3
Classifier: Programming Language :: Python :: 3.8
Classifier: Programming Language :: Python :: 3.9
Classifier: Programming Language :: Python :: 3.10
Classifier: Programming Language :: Python :: 3.11
Classifier: Programming Language :: Python :: 3.12
Requires-Python: >=3.8
Requires-Dist: httpx>=0.26.0
Requires-Dist: playwright>=1.40.0
Requires-Dist: pylance>=0.10.15
Requires-Dist: typing-extensions>=4.0.0
